imagepig/__init__.py
imagepig/api.py
imagepig-1.0.7.dist-info/LICENSE
imagepig-1.0.7.dist-info/METADATA
imagepig-1.0.7.dist-info/WHEEL
imagepig-1.0.7.dist-info/top_level.txt
imagepig-1.0.7.dist-info/RECORD
