Metadata-Version: 2.1
Name: imagepig
Version: 1.0.7
Summary: Package to use Image Pig, the API for AI images
Author-email: Pavel Mises <pavel@double.plus>
Project-URL: Homepage, https://imagepig.com/
Project-URL: Repository, https://github.com/double-plus/imagepig-python
Project-URL: Issues, https://github.com/double-plus/imagepig-python/issues
Project-URL: Documentation, https://imagepig.com/docs/
Classifier: Programming Language :: Python :: 3
Classifier: License :: OSI Approved :: MIT License
Classifier: Operating System :: OS Independent
Requires-Python: >=3.8
License-File: LICENSE
Requires-Dist: requests
